{ 
    "Level":  [
    {
        "QuestionImg":"1", 
        "Question":"Text_Color_Question1",
        "SelectionNum":4,
        "SelectionTxt_1":"Text_Color_Selection1",
        "SelectionTxt_2":"Text_Color_Selection2",                   
        "SelectionTxt_3":"Text_Color_Selection3",                   
        "SelectionTxt_4":"Text_Color_Selection4",                   
        "SelectionImg_1":"",                   
        "SelectionImg_2":"",                   
        "SelectionImg_3":"",                   
        "SelectionImg_4":"",            
        "SelectionTag_1":[3],
        "SelectionTag_2":[1],
        "SelectionTag_3":[2],
        "SelectionTag_4":[4],
        "SelectPercent_1":12,
        "SelectPercent_2":44,
        "SelectPercent_3":16,
        "SelectPercent_4":28     
    },
    {
        "QuestionImg":"2", 
        "Question":"Text_Color_Question2",
        "SelectionNum":4,
        "SelectionTxt_1":"Text_Color_Selection5",
        "SelectionTxt_2":"Text_Color_Selection6",                   
        "SelectionTxt_3":"Text_Color_Selection7",                   
        "SelectionTxt_4":"Text_Color_Selection8",                   
        "SelectionImg_1":"",                   
        "SelectionImg_2":"",                   
        "SelectionImg_3":"",                   
        "SelectionImg_4":"",            
        "SelectionTag_1":[5],
        "SelectionTag_2":[2],
        "SelectionTag_3":[3],
        "SelectionTag_4":[5],
        "SelectPercent_1":17,
        "SelectPercent_2":43,
        "SelectPercent_3":28,
        "SelectPercent_4":14          

    },
    {
        "QuestionImg":"3", 
        "Question":"Text_Color_Question3",
        "SelectionNum":2,
        "SelectionTxt_1":"Text_Color_Selection9",
        "SelectionTxt_2":"Text_Color_Selection10",                   
        "SelectionTxt_3":"",                   
        "SelectionTxt_4":"",                   
        "SelectionImg_1":"",                   
        "SelectionImg_2":"",                   
        "SelectionImg_3":"",                   
        "SelectionImg_4":"",            
        "SelectionTag_1":[3],
        "SelectionTag_2":[1],
        "SelectionTag_3":[],
        "SelectionTag_4":[],
        "SelectPercent_1":57,
        "SelectPercent_2":43,
        "SelectPercent_3":0,
        "SelectPercent_4":0             

    },
    {
        "QuestionImg":"4", 
        "Question":"Text_Color_Question4",
        "SelectionNum":2,
        "SelectionTxt_1":"Text_Color_Selection11",
        "SelectionTxt_2":"Text_Color_Selection12",                   
        "SelectionTxt_3":"",                   
        "SelectionTxt_4":"",                   
        "SelectionImg_1":"",                   
        "SelectionImg_2":"",                   
        "SelectionImg_3":"",                   
        "SelectionImg_4":"",            
        "SelectionTag_1":[5],
        "SelectionTag_2":[2],
        "SelectionTag_3":[],
        "SelectionTag_4":[],
        "SelectPercent_1":54,
        "SelectPercent_2":46,
        "SelectPercent_3":0,
        "SelectPercent_4":0                  

    },
    {
        "QuestionImg":"5", 
        "Question":"Text_Color_Question5",
        "SelectionNum":2,
        "SelectionTxt_1":"Text_Color_Selection13",
        "SelectionTxt_2":"Text_Color_Selection14",                   
        "SelectionTxt_3":"",                   
        "SelectionTxt_4":"",                   
        "SelectionImg_1":"",                   
        "SelectionImg_2":"",                   
        "SelectionImg_3":"",                   
        "SelectionImg_4":"",            
        "SelectionTag_1":[5],
        "SelectionTag_2":[4],
        "SelectionTag_3":[],
        "SelectionTag_4":[],
        "SelectPercent_1":62,
        "SelectPercent_2":38,
        "SelectPercent_3":0,
        "SelectPercent_4":0             

    },
    {
        "QuestionImg":"6", 
        "Question":"Text_Color_Question6",
        "SelectionNum":3,
        "SelectionTxt_1":"Text_Color_Selection15",
        "SelectionTxt_2":"Text_Color_Selection16",                   
        "SelectionTxt_3":"Text_Color_Selection17",                   
        "SelectionTxt_4":"",                   
        "SelectionImg_1":"",                   
        "SelectionImg_2":"",                   
        "SelectionImg_3":"",                   
        "SelectionImg_4":"",            
        "SelectionTag_1":[2],
        "SelectionTag_2":[3],
        "SelectionTag_3":[1],
        "SelectionTag_4":[],
        "SelectPercent_1":35,
        "SelectPercent_2":19,
        "SelectPercent_3":46,
        "SelectPercent_4":0              

    },
    {
        "QuestionImg":"7", 
        "Question":"Text_Color_Question7",
        "SelectionNum":3,
        "SelectionTxt_1":"Text_Color_Selection18",
        "SelectionTxt_2":"Text_Color_Selection19",                   
        "SelectionTxt_3":"Text_Color_Selection20",                   
        "SelectionTxt_4":"",                   
        "SelectionImg_1":"",                   
        "SelectionImg_2":"",                   
        "SelectionImg_3":"",                   
        "SelectionImg_4":"",            
        "SelectionTag_1":[1],
        "SelectionTag_2":[5],
        "SelectionTag_3":[3],
        "SelectionTag_4":[],
        "SelectPercent_1":21,
        "SelectPercent_2":33,
        "SelectPercent_3":46,
        "SelectPercent_4":0                  

    },
    {
        "QuestionImg":"8", 
        "Question":"Text_Color_Question8",
        "SelectionNum":4,
        "SelectionTxt_1":"Text_Color_Selection21",
        "SelectionTxt_2":"Text_Color_Selection22",                   
        "SelectionTxt_3":"Text_Color_Selection23",                   
        "SelectionTxt_4":"Text_Color_Selection24",                   
        "SelectionImg_1":"",                   
        "SelectionImg_2":"",                   
        "SelectionImg_3":"",              
        "SelectionImg_4":"",            
        "SelectionTag_1":[2],
        "SelectionTag_2":[1],
        "SelectionTag_3":[4],
        "SelectionTag_4":[3],
        "SelectPercent_1":39,
        "SelectPercent_2":19,
        "SelectPercent_3":12,
        "SelectPercent_4":30                   

    },
    {
        "QuestionImg":"9", 
        "Question":"Text_Color_Question9",
        "SelectionNum":4,
        "SelectionTxt_1":"Text_Color_Selection25",
        "SelectionTxt_2":"Text_Color_Selection26",                   
        "SelectionTxt_3":"Text_Color_Selection27",                   
        "SelectionTxt_4":"Text_Color_Selection28",                   
        "SelectionImg_1":"",                   
        "SelectionImg_2":"",                   
        "SelectionImg_3":"",              
        "SelectionImg_4":"",            
        "SelectionTag_1":[3],
        "SelectionTag_2":[2],
        "SelectionTag_3":[5],
        "SelectionTag_4":[1],
        "SelectPercent_1":27,
        "SelectPercent_2":24,
        "SelectPercent_3":24,
        "SelectPercent_4":25               

    },
    {
        "QuestionImg":"10", 
        "Question":"Text_Color_Question10",
        "SelectionNum":4,
        "SelectionTxt_1":"Text_Color_Selection29",
        "SelectionTxt_2":"Text_Color_Selection30",                   
        "SelectionTxt_3":"Text_Color_Selection31",                   
        "SelectionTxt_4":"Text_Color_Selection32",                   
        "SelectionImg_1":"",                   
        "SelectionImg_2":"",                   
        "SelectionImg_3":"",              
        "SelectionImg_4":"",            
        "SelectionTag_1":[3],
        "SelectionTag_2":[1],
        "SelectionTag_3":[2],
        "SelectionTag_4":[4],
        "SelectPercent_1":22,
        "SelectPercent_2":16,
        "SelectPercent_3":40,
        "SelectPercent_4":22                    

    },
    {
        "QuestionImg":"11", 
        "Question":"Text_Color_Question11",
        "SelectionNum":2,
        "SelectionTxt_1":"Text_Color_Selection33",
        "SelectionTxt_2":"Text_Color_Selection34",                   
        "SelectionTxt_3":"",                   
        "SelectionTxt_4":"",                   
        "SelectionImg_1":"",                   
        "SelectionImg_2":"",                   
        "SelectionImg_3":"",              
        "SelectionImg_4":"",            
        "SelectionTag_1":[4],
        "SelectionTag_2":[2],
        "SelectionTag_3":[],
        "SelectionTag_4":[],
        "SelectPercent_1":19,
        "SelectPercent_2":81,
        "SelectPercent_3":0,
        "SelectPercent_4":0               

    },
    {
        "QuestionImg":"12", 
        "Question":"Text_Color_Question12",
        "SelectionNum":2,
        "SelectionTxt_1":"Text_Color_Selection35",
        "SelectionTxt_2":"Text_Color_Selection36",                   
        "SelectionTxt_3":"",                   
        "SelectionTxt_4":"",                   
        "SelectionImg_1":"",                   
        "SelectionImg_2":"",                   
        "SelectionImg_3":"",                   
        "SelectionImg_4":"",            
        "SelectionTag_1":[3],
        "SelectionTag_2":[1],
        "SelectionTag_3":[],
        "SelectionTag_4":[],
        "SelectPercent_1":66,
        "SelectPercent_2":34,
        "SelectPercent_3":0,
        "SelectPercent_4":0               

    },
    {
        "QuestionImg":"13", 
        "Question":"Text_Color_Question13",
        "SelectionNum":2,
        "SelectionTxt_1":"Text_Color_Selection37",
        "SelectionTxt_2":"Text_Color_Selection38",                   
        "SelectionTxt_3":"",                   
        "SelectionTxt_4":"",                   
        "SelectionImg_1":"",                   
        "SelectionImg_2":"",                   
        "SelectionImg_3":"",              
        "SelectionImg_4":"",            
        "SelectionTag_1":[4],
        "SelectionTag_2":[2],
        "SelectionTag_3":[],
        "SelectionTag_4":[],
        "SelectPercent_1":52,
        "SelectPercent_2":48,
        "SelectPercent_3":0,
        "SelectPercent_4":0                  

    },
    {
        "QuestionImg":"14", 
        "Question":"Text_Color_Question14",
        "SelectionNum":2,
        "SelectionTxt_1":"Text_Color_Selection39",
        "SelectionTxt_2":"Text_Color_Selection40",                   
        "SelectionTxt_3":"",                   
        "SelectionTxt_4":"",                   
        "SelectionImg_1":"",                   
        "SelectionImg_2":"",                   
        "SelectionImg_3":"",              
        "SelectionImg_4":"",            
        "SelectionTag_1":[3],
        "SelectionTag_2":[5],
        "SelectionTag_3":[],
        "SelectionTag_4":[],
        "SelectPercent_1":76,
        "SelectPercent_2":24,
        "SelectPercent_3":0,
        "SelectPercent_4":0               

    },
    {
        "QuestionImg":"15", 
        "Question":"Text_Color_Question15",
        "SelectionNum":3,
        "SelectionTxt_1":"Text_Color_Selection41",
        "SelectionTxt_2":"Text_Color_Selection42",                   
        "SelectionTxt_3":"Text_Color_Selection43",                   
        "SelectionTxt_4":"",                   
        "SelectionImg_1":"",                   
        "SelectionImg_2":"",                   
        "SelectionImg_3":"",              
        "SelectionImg_4":"",            
        "SelectionTag_1":[2],
        "SelectionTag_2":[1],
        "SelectionTag_3":[4],
        "SelectionTag_4":[],
        "SelectPercent_1":46,
        "SelectPercent_2":31,
        "SelectPercent_3":23,
        "SelectPercent_4":0                    

    },
    {
        "QuestionImg":"16", 
        "Question":"Text_Color_Question16",
        "SelectionNum":4,
        "SelectionTxt_1":"Text_Color_Selection44",
        "SelectionTxt_2":"Text_Color_Selection45",                   
        "SelectionTxt_3":"Text_Color_Selection46",                   
        "SelectionTxt_4":"Text_Color_Selection47",                   
        "SelectionImg_1":"",                   
        "SelectionImg_2":"",                   
        "SelectionImg_3":"",              
        "SelectionImg_4":"",            
        "SelectionTag_1":[3],
        "SelectionTag_2":[5],
        "SelectionTag_3":[2],
        "SelectionTag_4":[4],
        "SelectPercent_1":28,
        "SelectPercent_2":17,
        "SelectPercent_3":33,
        "SelectPercent_4":22                

    },
    {
        "QuestionImg":"17", 
        "Question":"Text_Color_Question17",
        "SelectionNum":4,
        "SelectionTxt_1":"Text_Color_Selection48",
        "SelectionTxt_2":"Text_Color_Selection49",                   
        "SelectionTxt_3":"Text_Color_Selection50",                   
        "SelectionTxt_4":"Text_Color_Selection51",                   
        "SelectionImg_1":"",                   
        "SelectionImg_2":"",                   
        "SelectionImg_3":"",              
        "SelectionImg_4":"",            
        "SelectionTag_1":[4],
        "SelectionTag_2":[2],
        "SelectionTag_3":[3],
        "SelectionTag_4":[1],
        "SelectPercent_1":17,
        "SelectPercent_2":16,
        "SelectPercent_3":28,
        "SelectPercent_4":39               

    },
    {
        "QuestionImg":"18",                   
        "Question":"Text_Color_Question18",
        "SelectionNum":4,
        "SelectionTxt_1":"Text_Color_Selection52",
        "SelectionTxt_2":"Text_Color_Selection53",                   
        "SelectionTxt_3":"Text_Color_Selection54",                   
        "SelectionTxt_4":"Text_Color_Selection55",
        "SelectionImg_1":"",                   
        "SelectionImg_2":"",                   
        "SelectionImg_3":"",              
        "SelectionImg_4":"",            
        "SelectionTag_1":[3],
        "SelectionTag_2":[2],
        "SelectionTag_3":[4],
        "SelectionTag_4":[5],
        "SelectPercent_1":25,
        "SelectPercent_2":33,
        "SelectPercent_3":34,
        "SelectPercent_4":8              

    },
    {
        "QuestionImg":"19", 
        "Question":"Text_Color_Question19",
        "SelectionNum":4,
        "SelectionTxt_1":"Text_Color_Selection56",
        "SelectionTxt_2":"Text_Color_Selection57",                   
        "SelectionTxt_3":"Text_Color_Selection58",                   
        "SelectionTxt_4":"Text_Color_Selection59",                   
        "SelectionImg_1":"",                   
        "SelectionImg_2":"",                   
        "SelectionImg_3":"",              
        "SelectionImg_4":"",            
        "SelectionTag_1":[2],
        "SelectionTag_2":[1],
        "SelectionTag_3":[3],
        "SelectionTag_4":[5],
        "SelectPercent_1":21,
        "SelectPercent_2":26,
        "SelectPercent_3":22,
        "SelectPercent_4":31               

    },
    {
        "QuestionImg":"20", 
        "Question":"Text_Color_Question20",
        "SelectionNum":4,
        "SelectionTxt_1":"Text_Color_Selection60",
        "SelectionTxt_2":"Text_Color_Selection61",                   
        "SelectionTxt_3":"Text_Color_Selection62",                   
        "SelectionTxt_4":"Text_Color_Selection63",                   
        "SelectionImg_1":"",                   
        "SelectionImg_2":"",                   
        "SelectionImg_3":"",              
        "SelectionImg_4":"",            
        "SelectionTag_1":[3],
        "SelectionTag_2":[1],
        "SelectionTag_3":[4],
        "SelectionTag_4":[2],
        "SelectPercent_1":27,
        "SelectPercent_2":31,
        "SelectPercent_3":18,
        "SelectPercent_4":24               

    }
]

}